README.md
setup.py
ephys_nlm/__init__.py
ephys_nlm/_ephys_nlm.py
ephys_nlm/_outputrecordingextractor.py
ephys_nlm.egg-info/PKG-INFO
ephys_nlm.egg-info/SOURCES.txt
ephys_nlm.egg-info/dependency_links.txt
ephys_nlm.egg-info/requires.txt
ephys_nlm.egg-info/top_level.txt