Metadata-Version: 1.1
Name: ephys-nlm
Version: 0.1.2
Summary: Non-local means denoising of multi-channel electrophysiology timeseries.
Home-page: UNKNOWN
Author: Jeremy Magland
Author-email: jmagland@flatironinstitute.org
License: UNKNOWN
Platform: UNKNOWN
Classifier: Programming Language :: Python :: 3
Classifier: License :: OSI Approved :: Apache Software License
Classifier: Operating System :: OS Independent
